pytimetag/Analyser.py
pytimetag/BenchMarker.py
pytimetag/__init__.py
pytimetag/datablock.py
pytimetag/datablockserialJIT.py
pytimetag/analysers/CounterAnalyser.py
pytimetag/analysers/DeltaMetaAnalyser.py
pytimetag/analysers/EncodingAnalyser.py
pytimetag/analysers/HistogramAnalyser.py
pytimetag/analysers/MiscellaneousAnalyser.py
pytimetag-2.1.4.dist-info/LICENSE
pytimetag-2.1.4.dist-info/METADATA
pytimetag-2.1.4.dist-info/WHEEL
pytimetag-2.1.4.dist-info/top_level.txt
pytimetag-2.1.4.dist-info/RECORD
