Metadata-Version: 2.1
Name: pytimetag
Version: 2.1.4
Summary: A data processing lib for TimeTag.
Author: Hwaipy
Author-email: hwaipy@gmail.com
License: gpl-3.0
Keywords: timetag,physics
Classifier: Development Status :: 5 - Production/Stable
Classifier: Intended Audience :: Developers
Classifier: Intended Audience :: End Users/Desktop
Classifier: License :: OSI Approved :: GNU General Public License v3 (GPLv3)
Classifier: Programming Language :: Python :: 3
Classifier: Programming Language :: Python :: 3.9
Classifier: Programming Language :: Python :: 3.10
Classifier: Programming Language :: Python :: 3.11
Requires-Python: >=3.8
License-File: LICENSE
Requires-Dist: numpy
Requires-Dist: msgpack
Requires-Dist: numba
